ffg/__init__.py
ffg/emitter/__init__.py
ffg/emitter/dot_emitter.py
ffg/emitter/yinyang_emitter.py
ffg/gen/__init__.py
ffg/gen/gen_configuration.py
ffg/gen/generator.py
ffg/gen/tree_generation.py
ffg/operators/__init__.py
ffg/operators/bitvector_theory.py
ffg/operators/boolean_theory.py
ffg/operators/generic.py
ffg/operators/integer_theory.py
ffg/operators/real_theory.py
ffg/operators/string_theory.py
ffg/visitors/__init__.py
ffg/visitors/compound_visitor.py
ffg/visitors/constant_visitor.py
ffg/visitors/dot_visitor.py
ffg/visitors/infix_printer_visitor.py
ffg/visitors/initialization_visitor.py
ffg/visitors/printer_visitor.py
ffg/visitors/rewrite_visitor.py
ffg/visitors/variable_visitor.py
ffg-0.1.2.dist-info/LICENSE
ffg-0.1.2.dist-info/METADATA
ffg-0.1.2.dist-info/WHEEL
ffg-0.1.2.dist-info/top_level.txt
ffg-0.1.2.dist-info/RECORD
