Metadata-Version: 2.1
Name: ffg
Version: 0.1.2
Summary: A generator of fusion functions for Semantic Fusion (YinYang).
Author: Nicola Dardanis, Lucas Weitzendorf
License: MIT
Project-URL: Source, https://github.com/nicdard/fusion-function-generator
Project-URL: Tracker, https://github.com/nicdard/fusion-function-generator/issues
License-File: LICENSE
